firetv/__init__.py
firetv/__main__.py
firetv-1.0.9.dist-info/LICENSE
firetv-1.0.9.dist-info/METADATA
firetv-1.0.9.dist-info/WHEEL
firetv-1.0.9.dist-info/entry_points.txt
firetv-1.0.9.dist-info/top_level.txt
firetv-1.0.9.dist-info/RECORD
