Metadata-Version: 2.1
Name: firetv
Version: 1.0.9
Summary: Communicate with an Amazon Fire TV device via ADB over a network.
Home-page: https://github.com/happyleavesaoc/python-firetv/
Author: happyleaves
Author-email: happyleaves.tfr@gmail.com
License: MIT
Platform: UNKNOWN
Classifier: License :: OSI Approved :: MIT License
Classifier: Operating System :: OS Independent
Classifier: Programming Language :: Python :: 2
Classifier: Programming Language :: Python :: 3
Requires-Dist: pycryptodome
Requires-Dist: rsa
Requires-Dist: adb-homeassistant
Requires-Dist: pure-python-adb-homeassistant
Provides-Extra: firetv-server
Requires-Dist: Flask (>=0.10.1); extra == 'firetv-server'
Requires-Dist: PyYAML (>=3.12); extra == 'firetv-server'
